[
  {
    "project": "PRJ03246 - Balance Point Control - BPC - Celle - Unknown Well - MFC_ MTT",
    "job": "N/A",
    "comment": "Standard ANSA processing required for ABI data.",
    "addedBy": "Leonard Lapiso",
    "date": "26-05-2026 12:44"
  },
  {
    "project": "PRJ03262 - SLB - SLB Denmark - DFA16 (MFA-16)_DFA18 (MFA-18)_DFB11 (MFB-11)_DFB21 (MFB-21) - MFC",
    "job": "N/A",
    "comment": "Decision on way forward to be decided by Total",
    "addedBy": "Abdilmalik Mohamed",
    "date": "26-05-2026 08:56"
  },
  {
    "project": "PRJ03261 - SLB - SLB Denmark - HBA21 (HBA-21)_HBA11 (HBA-11) - MFC",
    "job": "N/A",
    "comment": "SLB to run FTET and exercise the TRSSSV then will be on standby until oilenco tool comes on board.\nLookahead has MFC run on Saturday afternoon",
    "addedBy": "Joshua Cheyne",
    "date": "26-05-2026 06:48"
  },
  {
    "project": "PRJ03262 - SLB - SLB Denmark - DFA16 (MFA-16)_DFA18 (MFA-18)_DFB11 (MFB-11)_DFB21 (MFB-21) - MFC",
    "job": "N/A",
    "comment": "DFB16 being flowed to see the affects of the Bluespark run on SPM 2/3. Decision of way ahead of to rig down or do another Bluespark and Caliper run to be decided in the morning.",
    "addedBy": "Abdilmalik Mohamed",
    "date": "25-05-2026 19:58"
  },
  {
    "project": "PRJ03246 - Balance Point Control - BPC - Celle - Unknown Well - MFC_ MTT",
    "job": "N/A",
    "comment": "LL travelling to Munich tomorrow. Expect to be ready to log ABI Wednesday afternoon or Thursday. Modified Telemetry cartridge arrives later on Wednesday. Operations on site are 7am-7pm. At this stage BPC will log their RSBT first and ABI is contingency if the client isn't happy with the data (Cement Evaluation in 18-5/8\" Casing).",
    "addedBy": "Leonard Lapiso",
    "date": "25-05-2026 18:51"
  }
]