[
  {
    "companyName": "ANSA",
    "numIn": 5,
    "names": [
      "Alan Walsh",
      "John Guntoro",
      "Craig Lamont",
      "Maurillio Addario",
      "Joseph Guyan"
    ]
  },
  {
    "companyName": "READ",
    "numIn": 5,
    "names": [
      "Ross Fraser",
      "Stewart Steele",
      "Rob Molina",
      "Mark Davidson",
      "Leonard Lapiso"
    ]
  },
  {
    "companyName": "HydraWell",
    "numIn": 5,
    "names": [
      "Liam Strath",
      "Cherie Bowden",
      "James Reid",
      "George Handsley",
      "Calum Smith"
    ]
  },
  {
    "companyName": "BlueSpark",
    "numIn": 0,
    "names": []
  },
  {
    "companyName": "OTS",
    "numIn": 1,
    "names": [
      "Colin Greig"
    ]
  },
  {
    "companyName": "Visitors",
    "numIn": 0,
    "names": []
  }
]