[
  {
    "companyName": "ANSA",
    "numIn": 5,
    "names": [
      "Mohamed Selim",
      "Craig Lamont",
      "Jay Purves",
      "Joseph Guyan",
      "Alan Walsh"
    ]
  },
  {
    "companyName": "READ",
    "numIn": 5,
    "names": [
      "Ross Fraser",
      "Thomas Dyke",
      "Chris Kennedy",
      "Stewart Steele",
      "Dave Simpson"
    ]
  },
  {
    "companyName": "HydraWell",
    "numIn": 2,
    "names": [
      "Cherie Bowden",
      "Liam Strath"
    ]
  },
  {
    "companyName": "BlueSpark",
    "numIn": 0,
    "names": []
  },
  {
    "companyName": "OTS",
    "numIn": 0,
    "names": []
  },
  {
    "companyName": "Visitors",
    "numIn": 0,
    "names": []
  }
]