[
  {
    "companyName": "ANSA",
    "numIn": 5,
    "names": [
      "Joseph Guyan",
      "Maurillio Addario",
      "Alan Walsh",
      "Craig Lamont",
      "John Guntoro"
    ]
  },
  {
    "companyName": "READ",
    "numIn": 6,
    "names": [
      "Rob Molina",
      "Mark Davidson",
      "Leonard Lapiso",
      "Melissa Hernandez",
      "Craig Fraser",
      "Ross Fraser"
    ]
  },
  {
    "companyName": "HydraWell",
    "numIn": 3,
    "names": [
      "Liam Strath",
      "Peter Thomson",
      "Calum Smith"
    ]
  },
  {
    "companyName": "BlueSpark",
    "numIn": 0,
    "names": []
  },
  {
    "companyName": "OTS",
    "numIn": 0,
    "names": []
  },
  {
    "companyName": "Visitors",
    "numIn": 1,
    "names": [
      "Jamie Duncan"
    ]
  }
]