[
  {
    "companyName": "ANSA",
    "numIn": 2,
    "names": [
      "Heather Caldwell",
      "Jenni Michie"
    ]
  },
  {
    "companyName": "READ",
    "numIn": 3,
    "names": [
      "Ross Fraser",
      "Mark Davidson",
      "Dave Simpson"
    ]
  },
  {
    "companyName": "HydraWell",
    "numIn": 5,
    "names": [
      "Peter Thomson",
      "James Reid",
      "George Handsley",
      "Liam Strath",
      "Calum Smith"
    ]
  },
  {
    "companyName": "BlueSpark",
    "numIn": 0,
    "names": []
  },
  {
    "companyName": "OTS",
    "numIn": 0,
    "names": []
  },
  {
    "companyName": "Visitors",
    "numIn": 0,
    "names": []
  }
]